{
    "type": "minecraft:crafting_shaped",
    "pattern": [
      "WDQ",
      "CRA",
      "IDQ"
    ],
    "key": {
      "I": { "item": "minecraft:iron_ingot" },
      "Q": { "item": "minecraft:quartz" },
      "D": { "item": "minecraft:diamond" },
      "R": { "item": "minecraft:redstone" },
      "A": { "item": "minecraft:amethyst_shard" },
      "C": { "item": "cobblemon:yellow_apricorn" },
      "W": { "item": "cobblemon:red_apricorn" }
    },
    "result": { "id": "cobblemon_smartphone:orange_smartphone", "count": 1 },
    "category": "misc"
}